{
    "available": false,
    "list": {
        "platinum": [
            {
                "img": "https://res.cloudinary.com/du73ags2q/image/upload/c_pad,h_100,w_200/v1560864759/012.AWS_logo_RGB_REV_oryfhx.png",
                "alt": "Amazon Web Services",
                "link": "https://aws.amazon.com"
            },
            {
                "img": "https://res.cloudinary.com/doxu4euiq/image/upload/c_pad,h_100,w_200/v1706679689/slsdays2024/logo-mantelgp.png",
                "alt": "Mantel Group",
                "link": "https://mantelgroup.com.au/"
            },
            {
                "img": "https://res.cloudinary.com/du73ags2q/image/upload/c_pad,h_100,w_200/v1713218407/slsdaysanz/lockup_GoogleCloud_Reverse_rgb_2900x512px.png",
                "alt": "Google Cloud",
                "link": "https://cloud.google.com/"
            }
        ],
        "gold": [
            {
                "img": "https://res.cloudinary.com/doxu4euiq/image/upload/c_pad,h_65,w_130/v1706679689/slsdays2024/logo-fastly.png",
                "alt": "Fastly",
                "link": "https://www.fastly.com/"
            },
            {
                "img": "https://res.cloudinary.com/du73ags2q/image/upload/c_pad,h_65,w_130/v1675125888/slsdaysanz/cloudshuttle-white-transparent.png",
                "alt": "CloudShuttle",
                "link": "https://www.cloudshuttle.com.au/"
            },
            {
                "img": "https://res.cloudinary.com/doxu4euiq/image/upload/c_pad,h_65,w_130/v1706679689/slsdays2024/logo-kaleida.png",
                "alt": "Kaleida",
                "link": "https://www.kaleida.team/"
            },
            {
                "img": "https://res.cloudinary.com/doxu4euiq/image/upload/c_pad,h_65,w_130/v1706679689/slsdays2024/logo-doit.png",
                "alt": "Doit",
                "link": "https://www.doit.com/"
            },
            {
                "img": "https://res.cloudinary.com/doxu4euiq/image/upload/c_pad,h_65,w_130/v1706679689/slsdays2024/logo-cevo.png",
                "alt": "Cevo",
                "link": "https://www.cevo.com.au/"
            },
            {
                "img": "https://res.cloudinary.com/du73ags2q/image/upload/c_pad,h_65,w_130/v1713218415/slsdaysanz/Logo_whit_2x.png",
                "alt": "Baseline",
                "link": "https://baselinejs.com/"
            },
            {
                "img": "https://res.cloudinary.com/du73ags2q/image/upload/c_pad,h_65,w_130/v1715498106/new_relic_logo_horizontal_white_ih69bp.png",
                "alt": "New Relic",
                "link": "https://newrelic.com/"
            },
            {
                "img": "https://res.cloudinary.com/du73ags2q/image/upload/c_pad,h_65,w_130/v1715497893/Logo_Full_-_White_xkeeog.png",
                "alt": "tina cms",
                "link": "https://tina.io/"
            }
        ],
        "silver": [
            {
                "img": "https://res.cloudinary.com/doxu4euiq/image/upload/c_pad,h_80,w_130/v1706679689/slsdays2024/logo-wiresuncrossed.png",
                "alt": "Wires Uncrossed",
                "link": "https://wue.co.nz/"
            },
            {
                "img": "https://res.cloudinary.com/doxu4euiq/image/upload/c_pad,h_65,w_130/v1706679689/slsdays2024/logo-apiconnects.png",
                "alt": "API Connects NZ",
                "link": "https://apiconnects.co.nz/"
            }
        ]
    }
}
